MANIFEST.in
README.rst
setup.py
smsbox/__init__.py
smsbox/commons.py
smsbox/debug.py
smsbox.egg-info/PKG-INFO
smsbox.egg-info/SOURCES.txt
smsbox.egg-info/dependency_links.txt
smsbox.egg-info/requires.txt
smsbox.egg-info/top_level.txt