Metadata-Version: 1.0
Name: smsbox
Version: 0.1.0
Summary: Python library for smsbox.sk API
Home-page: https://github.com/PragmaticMates/python-smsbox
Author: Pragmatic Mates
Author-email: info@pragmaticmates.com
License: BSD License
Keywords: python sms api library sending
Platform: UNKNOWN
Classifier: Programming Language :: Python
Classifier: Programming Language :: Python :: 2.5
Classifier: Programming Language :: Python :: 2.6
Classifier: Programming Language :: Python :: 2.7
Classifier: Operating System :: OS Independent
Classifier: Environment :: Web Environment
Classifier: Intended Audience :: Developers
Classifier: License :: OSI Approved :: BSD License
Classifier: Development Status :: 3 - Alpha
